emailpatterns/__init__.py
emailpatterns/utils.py
emailpatterns-1.1.0.dist-info/licenses/LICENCE
emailpatterns-1.1.0.dist-info/METADATA
emailpatterns-1.1.0.dist-info/WHEEL
emailpatterns-1.1.0.dist-info/top_level.txt
emailpatterns-1.1.0.dist-info/RECORD
