Metadata-Version: 2.4
Name: emailpatterns
Version: 1.1.0
Summary: Shared Email Pattern Generator
Home-page: https://github.com/pupattan/emailpatterns
Author: Pulak Pattanayak
Author-email: pulak.pattanayak@gmail.com
Classifier: Programming Language :: Python :: 3
Classifier: License :: OSI Approved :: MIT License
Classifier: Operating System :: OS Independent
Requires-Python: >=3.8
License-File: LICENCE
Dynamic: author
Dynamic: author-email
Dynamic: classifier
Dynamic: description
Dynamic: description-content-type
Dynamic: home-page
Dynamic: license-file
Dynamic: requires-python
Dynamic: summary
